verilog practice/greater_than.v
module greater_than (A, B, F);

input [1:0] A, B;
output F;

assign F = (A > B);

// assign F = (A[1] & ~B[1]) | (A[0] & ~B[1] & ~B[0]) | (A[1] & A[0] & ~B[0]);

endmodule

verilog practice/greater_than_tb.v
`timescale  1ns/1ns
`include "greater_than.v"

module greater_than_tb;

reg [1:0] A, B;
wire F;

greater_than uut(A, B, F);

initial begin

	$dumpfile("greater_than_tb.vcd");
	$dumpvars(0, greater_than_tb);

	A = 2'd0; B = 2'd0; #20;
	A = 2'd0; B = 2'd1; #20;
	A = 2'd0; B = 2'd2; #20;
	A = 2'd0; B = 2'd3; #20;
	A = 2'd1; B = 2'd0; #20;
	A = 2'd1; B = 2'd1; #20;
	A = 2'd1; B = 2'd2; #20;
	A = 2'd1; B = 2'd3; #20;
	A = 2'd2; B = 2'd0; #20;
	A = 2'd2; B = 2'd1; #20;
	A = 2'd2; B = 2'd2; #20;
	A = 2'd2; B = 2'd3; #20;
	A = 2'd3; B = 2'd0; #20;
	A = 2'd3; B = 2'd1; #20;
	A = 2'd3; B = 2'd2; #20;
	A = 2'd3; B = 2'd3; #20;
	
	$display("Test complite");
end

endmodule

verilog practice/greater_than_tb.vcd
$date
	Sat Jun 01 14:11:29 2024
$end
$version
	Icarus Verilog
$end
$timescale
	1ns
$end
$scope module greater_than_tb $end
$var wire 1 ! F $end
$var reg 2 " A [1:0] $end
$var reg 2 # B [1:0] $end
$scope module uut $end
$var wire 2 $ A [1:0] $end
$var wire 2 % B [1:0] $end
$var wire 1 ! F $end
$upscope $end
$upscope $end
$enddefinitions $end
#0
$dumpvars
b0 %
b0 $
b0 #
b0 "
0!
$end
#20
b1 #
b1 %
#40
b10 #
b10 %
#60
b11 #
b11 %
#80
1!
b0 #
b0 %
b1 "
b1 $
#100
0!
b1 #
b1 %
#120
b10 #
b10 %
#140
b11 #
b11 %
#160
1!
b0 #
b0 %
b10 "
b10 $
#180
b1 #
b1 %
#200
0!
b10 #
b10 %
#220
b11 #
b11 %
#240
1!
b0 #
b0 %
b11 "
b11 $
#260
b1 #
b1 %
#280
b10 #
b10 %
#300
0!
b11 #
b11 %
