verilog practice/sequentialDemo.v
module top(A, B, CLK, Z);

input A, B, CLK;
output Z;

reg D = 0;

assign Z = D;

always @(posedge CLK) 
begin
	D = A ^ B ^ D;	
end

endmodule

verilog practice/sequentialDemo_tb.v
`timescale 1ns/1ns
`include "sequentialDemo.v"

module sequentialDemo_tb;

reg A, B, CLK = 0;
wire Z;

top UUT(A, B, CLK, Z);

always begin
	CLK = ~CLK;
	#10;
end

initial begin
	$dumpfile("sequentialDemo_tb.vcd");
	$dumpvars(0, sequentialDemo_tb);

	{A, B} = 2'b00; #20;
	{A, B} = 2'b11; #20;
	{A, B} = 2'b01; #20;
	{A, B} = 2'b00; #20;
	{A, B} = 2'b11; #20;
	{A, B} = 2'b10; #20;
	{A, B} = 2'b01; #20;
	{A, B} = 2'b10; #20;
	$finish;
end

endmodule

verilog practice/sequentialDemo_tb.vcd
$date
	Mon Jun 03 11:09:44 2024
$end
$version
	Icarus Verilog
$end
$timescale
	1ns
$end
$scope module sequentialDemo_tb $end
$var wire 1 ! Z $end
$var reg 1 " A $end
$var reg 1 # B $end
$var reg 1 $ CLK $end
$scope module UUT $end
$var wire 1 " A $end
$var wire 1 # B $end
$var wire 1 $ CLK $end
$var wire 1 ! Z $end
$var reg 1 % D $end
$upscope $end
$upscope $end
$enddefinitions $end
#0
$dumpvars
0%
1$
0#
0"
0!
$end
#10
0$
#20
1$
1"
1#
#30
0$
#40
1!
1%
1$
0"
#50
0$
#60
1$
0#
#70
0$
#80
1$
1"
1#
#90
0$
#100
0!
0%
1$
0#
#110
0$
#120
1!
1%
1$
0"
1#
#130
0$
#140
0!
0%
1$
1"
0#
#150
0$
#160
1!
1%
1$
