verilog practice/decoder5-to-32/532.v

// 5 to 32 decoder
module decoder5to32(A, D);

input [4:0]A;
output [31:0]D;

wire [11:0]W;

decoder3to8 u0(.A(A[4:2]), .D(W[11:4]));
decoder2to4 u1(.A(A[1:0]), .D(W[3:0]));

assign D[31] = W[11] & W[3];
assign D[30] = W[11] & W[2];
assign D[29] = W[11] & W[1];
assign D[28] = W[11] & W[0];

assign D[27] = W[10] & W[3];
assign D[26] = W[10] & W[2];
assign D[25] = W[10] & W[1];
assign D[24] = W[10] & W[0];

assign D[23] = W[9] & W[3];
assign D[22] = W[9] & W[2];
assign D[21] = W[9] & W[1];
assign D[20] = W[9] & W[0];

assign D[19] = W[8] & W[3];
assign D[18] = W[8] & W[2];
assign D[17] = W[8] & W[1];
assign D[16] = W[8] & W[0];

assign D[15] = W[7] & W[3];
assign D[14] = W[7] & W[2];
assign D[13] = W[7] & W[1];
assign D[12] = W[7] & W[0];

assign D[11] = W[6] & W[3];
assign D[10] = W[6] & W[2];
assign D[9] = W[6] & W[1];
assign D[8] = W[6] & W[0];

assign D[7] = W[5] & W[3];
assign D[6] = W[5] & W[2];
assign D[5] = W[5] & W[1];
assign D[4] = W[5] & W[0];

assign D[3] = W[4] & W[3];
assign D[2] = W[4] & W[2];
assign D[1] = W[4] & W[1];
assign D[0] = W[4] & W[0];


endmodule



// 3 to 8 decoder
module decoder3to8(A, D);

input [2:0]A;
output [7:0]D;

wire [5:0]W;

decoder2to4 u0(.A(A[2:1]), .D(W[5:2]));
decoder1to2 u1(.A(A[0]), .D(W[1:0]));

assign D[7] = W[5] & W[1];
assign D[6] = W[5] & W[0];
assign D[5] = W[4] & W[1];
assign D[4] = W[4] & W[0];
assign D[3] = W[3] & W[1];
assign D[2] = W[3] & W[0];
assign D[1] = W[2] & W[1];
assign D[0] = W[2] & W[0];

endmodule


//2 to 4 decoder
module decoder2to4(A, D);

input [1:0]A;
output [3:0]D;

wire [3:0]W;

decoder1to2 u0(.A(A[1]), .D(W[3:2]));
decoder1to2 u1(.A(A[0]), .D(W[1:0]));

// AND gates 

assign D[3] = W[3] & W[1];
assign D[2] = W[3] & W[0];
assign D[1] = W[2] & W[1];
assign D[0] = W[2] & W[0];

endmodule


//1 to 2 decoder
module decoder1to2(A, D);

input A;
output [1:0]D;

assign D[1] = ~A;
assign D[0] = A;

endmodule

verilog practice/decoder5-to-32/decoder5to32_tb.v
`timescale 1ns/1ns
`include "532.v"

module decoder5to32_tb;

reg [4:0]A;
wire [31:0]D;

decoder5to32 uut(A, D);

integer i = 0;

initial begin
	$dumpfile("decoder5to32_tb.vcd");
	$dumpvars(0, decoder5to32_tb);

	for (i = 0; i < 32; i = i + 1) begin 
		A = i; #20;
	end


end

endmodule

verilog practice/decoder5-to-32/decoder5to32_tb.vcd
$date
	Tue Jun 04 00:31:25 2024
$end
$version
	Icarus Verilog
$end
$timescale
	1ns
$end
$scope module decoder5to32_tb $end
$var wire 32 ! D [31:0] $end
$var reg 5 " A [4:0] $end
$var integer 32 # i [31:0] $end
$scope module uut $end
$var wire 5 $ A [4:0] $end
$var wire 12 % W [11:0] $end
$var wire 32 & D [31:0] $end
$scope module u0 $end
$var wire 3 ' A [2:0] $end
$var wire 6 ( W [5:0] $end
$var wire 8 ) D [7:0] $end
$scope module u0 $end
$var wire 2 * A [1:0] $end
$var wire 4 + W [3:0] $end
$var wire 4 , D [3:0] $end
$scope module u0 $end
$var wire 1 - A $end
$var wire 2 . D [1:0] $end
$upscope $end
$scope module u1 $end
$var wire 1 / A $end
$var wire 2 0 D [1:0] $end
$upscope $end
$upscope $end
$scope module u1 $end
$var wire 1 1 A $end
$var wire 2 2 D [1:0] $end
$upscope $end
$upscope $end
$scope module u1 $end
$var wire 2 3 A [1:0] $end
$var wire 4 4 W [3:0] $end
$var wire 4 5 D [3:0] $end
$scope module u0 $end
$var wire 1 6 A $end
$var wire 2 7 D [1:0] $end
$upscope $end
$scope module u1 $end
$var wire 1 8 A $end
$var wire 2 9 D [1:0] $end
$upscope $end
$upscope $end
$upscope $end
$upscope $end
$enddefinitions $end
#0
$dumpvars
b10 9
08
b10 7
06
b1000 5
b1010 4
b0 3
b10 2
01
b10 0
0/
b10 .
0-
b1000 ,
b1010 +
b0 *
b10000000 )
b100010 (
b0 '
b10000000000000000000000000000000 &
b100000001000 %
b0 $
b0 #
b0 "
b10000000000000000000000000000000 !
$end
#20
b1000000000000000000000000000000 !
b1000000000000000000000000000000 &
b100000000100 %
b100 5
b1001 4
b1 9
18
b1 3
b1 "
b1 $
b1 #
#40
b100000000000000000000000000000 !
b100000000000000000000000000000 &
b100000000010 %
b10 5
b1 7
16
b110 4
b10 9
08
b10 3
b10 "
b10 $
b10 #
#60
b10000000000000000000000000000 !
b10000000000000000000000000000 &
b100000000001 %
b1 5
b101 4
b1 9
18
b11 3
b11 "
b11 $
b11 #
#80
b1000000000000000000000000000 !
b1000000000000000000000000000 &
b1000000 )
b10000001000 %
b1000 5
b100001 (
b1 2
11
b10 7
06
b1010 4
b10 9
08
b1 '
b0 3
b100 "
b100 $
b100 #
#100
b100000000000000000000000000 !
b100000000000000000000000000 &
b10000000100 %
b100 5
b1001 4
b1 9
18
b1 3
b101 "
b101 $
b101 #
#120
b10000000000000000000000000 !
b10000000000000000000000000 &
b10000000010 %
b10 5
b1 7
16
b110 4
b10 9
08
b10 3
b110 "
b110 $
b110 #
#140
b1000000000000000000000000 !
b1000000000000000000000000 &
b10000000001 %
b1 5
b101 4
b1 9
18
b11 3
b111 "
b111 $
b111 #
#160
b100000000000000000000000 !
b100000000000000000000000 &
b100 ,
b100000 )
b1000001000 %
b1000 5
b1001 +
b1 0
1/
b1 *
b10010 (
b10 2
01
b10 7
06
b1010 4
b10 9
08
b10 '
b0 3
b1000 "
b1000 $
b1000 #
#180
b10000000000000000000000 !
b10000000000000000000000 &
b1000000100 %
b100 5
b1001 4
b1 9
18
b1 3
b1001 "
b1001 $
b1001 #
#200
b1000000000000000000000 !
b1000000000000000000000 &
b1000000010 %
b10 5
b1 7
16
b110 4
b10 9
08
b10 3
b1010 "
b1010 $
b1010 #
#220
b100000000000000000000 !
b100000000000000000000 &
b1000000001 %
b1 5
b101 4
b1 9
18
b11 3
b1011 "
b1011 $
b1011 #
#240
b10000000000000000000 !
b10000000000000000000 &
b10000 )
b100001000 %
b1000 5
b10001 (
b1 2
11
b10 7
06
b1010 4
b10 9
08
b11 '
b0 3
b1100 "
b1100 $
b1100 #
#260
b1000000000000000000 !
b1000000000000000000 &
b100000100 %
b100 5
b1001 4
b1 9
18
b1 3
b1101 "
b1101 $
b1101 #
#280
b100000000000000000 !
b100000000000000000 &
b100000010 %
b10 5
b1 7
16
b110 4
b10 9
08
b10 3
b1110 "
b1110 $
b1110 #
#300
b10000000000000000 !
b10000000000000000 &
b100000001 %
b1 5
b101 4
b1 9
18
b11 3
b1111 "
b1111 $
b1111 #
#320
b1000000000000000 !
b1000000000000000 &
b10 ,
b1000 )
b10001000 %
b1000 5
b1 .
1-
b110 +
b10 0
0/
b10 *
b1010 (
b10 2
01
b10 7
06
b1010 4
b10 9
08
b100 '
b0 3
b10000 "
b10000 $
b10000 #
#340
b100000000000000 !
b100000000000000 &
b10000100 %
b100 5
b1001 4
b1 9
18
b1 3
b10001 "
b10001 $
b10001 #
#360
b10000000000000 !
b10000000000000 &
b10000010 %
b10 5
b1 7
16
b110 4
b10 9
08
b10 3
b10010 "
b10010 $
b10010 #
#380
b1000000000000 !
b1000000000000 &
b10000001 %
b1 5
b101 4
b1 9
18
b11 3
b10011 "
b10011 $
b10011 #
#400
b100000000000 !
b100000000000 &
b100 )
b1001000 %
b1000 5
b1001 (
b1 2
11
b10 7
06
b1010 4
b10 9
08
b101 '
b0 3
b10100 "
b10100 $
b10100 #
#420
b10000000000 !
b10000000000 &
b1000100 %
b100 5
b1001 4
b1 9
18
b1 3
b10101 "
b10101 $
b10101 #
#440
b1000000000 !
b1000000000 &
b1000010 %
b10 5
b1 7
16
b110 4
b10 9
08
b10 3
b10110 "
b10110 $
b10110 #
#460
b100000000 !
b100000000 &
b1000001 %
b1 5
b101 4
b1 9
18
b11 3
b10111 "
b10111 $
b10111 #
#480
b10000000 !
b10000000 &
b1 ,
b10 )
b101000 %
b1000 5
b101 +
b1 0
1/
b11 *
b110 (
b10 2
01
b10 7
06
b1010 4
b10 9
08
b110 '
b0 3
b11000 "
b11000 $
b11000 #
#500
b1000000 !
b1000000 &
b100100 %
b100 5
b1001 4
b1 9
18
b1 3
b11001 "
b11001 $
b11001 #
#520
b100000 !
b100000 &
b100010 %
b10 5
b1 7
16
b110 4
b10 9
08
b10 3
b11010 "
b11010 $
b11010 #
#540
b10000 !
b10000 &
b100001 %
b1 5
b101 4
b1 9
18
b11 3
b11011 "
b11011 $
b11011 #
#560
b1000 !
b1000 &
b1 )
b11000 %
b1000 5
b101 (
b1 2
11
b10 7
06
b1010 4
b10 9
08
b111 '
b0 3
b11100 "
b11100 $
b11100 #
#580
b100 !
b100 &
b10100 %
b100 5
b1001 4
b1 9
18
b1 3
b11101 "
b11101 $
b11101 #
#600
b10 !
b10 &
b10010 %
b10 5
b1 7
16
b110 4
b10 9
08
b10 3
b11110 "
b11110 $
b11110 #
#620
b1 !
b1 &
b10001 %
b1 5
b101 4
b1 9
18
b11 3
b11111 "
b11111 $
b11111 #
#640
b100000 #
